setup.py
compute_overtime/ComputeOvertime.py
compute_overtime/__init__.py
compute_overtime.egg-info/PKG-INFO
compute_overtime.egg-info/SOURCES.txt
compute_overtime.egg-info/dependency_links.txt
compute_overtime.egg-info/not-zip-safe
compute_overtime.egg-info/top_level.txt