Metadata-Version: 1.0
Name: compute-overtime
Version: 0.2
Summary: Computation of Worked Overtime
Home-page: UNKNOWN
Author: Ikenna Nwosu
Author-email: ikenna.nwosu@kositechconsultingltd.com
License: UNKNOWN
Platform: UNKNOWN
